Metadata-Version: 2.1
Name: oneNeuron-pypi-pra2465
Version: 0.0.1
Summary: its an Implementation of Perceptron
Home-page: https://github.com/pra2465/oneNeuron_pypi
Author: USER_NAME
Author-email: prateek.shankar01@gmail.com
License: UNKNOWN
Project-URL: Bug Tracker, https://github.com/pra2465/oneNeuron_pypi/issues
Platform: UNKNOWN
Classifier: Programming Language :: Python :: 3
Classifier: License :: OSI Approved :: MIT License
Classifier: Operating System :: OS Independent
Requires-Python: >=3.7
License-File: LICENSE
Requires-Dist: numpy
Requires-Dist: tqdm
Requires-Dist: logging
